[
  {
    "id": "a6b055a0-1605-47af-a5a9-f7dec6f181a0",
    "data": [
      {
        "text": "dessert",
        "userDefined": false
      }
    ],
    "isTemplate": false,
    "count": 1,
    "lang": "en",
    "updated": 0
  },
  {
    "id": "71b40544-dc85-4f9e-8285-6d28b1aca2e0",
    "data": [
      {
        "text": "3",
        "meta": "@sys.number",
        "alias": "number",
        "userDefined": false
      }
    ],
    "isTemplate": false,
    "count": 0,
    "lang": "en",
    "updated": 0
  }
]